goat_adapters/crewai/__init__.py
goat_adapters/crewai/adapter.py
goat_sdk_adapter_crewai-0.1.0.dist-info/METADATA
goat_sdk_adapter_crewai-0.1.0.dist-info/WHEEL
goat_sdk_adapter_crewai-0.1.0.dist-info/RECORD
