Metadata-Version: 2.1
Name: goat-sdk-adapter-crewai
Version: 0.1.0
Summary: Goat adapter for CrewAI
Home-page: https://ohmygoat.dev/
Keywords: goat,sdk,web3,agents,ai,crewai
Author: Andrea Villa
Author-email: andreakarimodm@gmail.com
Requires-Python: >=3.10,<3.13
Classifier: Programming Language :: Python :: 3
Classifier: Programming Language :: Python :: 3.10
Classifier: Programming Language :: Python :: 3.11
Classifier: Programming Language :: Python :: 3.12
Requires-Dist: crewai (>=0.108.0)
Requires-Dist: goat-sdk (>=0.1.6)
Project-URL: Bug Tracker, https://github.com/goat-sdk/goat/issues
Project-URL: Repository, https://github.com/goat-sdk/goat
